{"inkVersion":21,"root":[["\n",{"->":"main"},["done",{"#f":5,"#n":"g-0"}],null],"done",{"main":[{"->":"Greeting"},{"#f":1}],"Greeting":["ev",{"VAR?":"talking"},false,"==","/ev",[{"->":".^.b","c":true},{"b":["\n","^Здрав будь, молодец ","#","^speaker:","ev",{"VAR?":"npc"},"out","/ev","^ ","/#","#","^portrait:","ev",{"VAR?":"npc_portrait"},"out","/ev","/#","\n","ev",true,"/ev",{"VAR=":"talking","re":true},{"->":".^.^.^.6"},null]}],"nop","\n",{"->":"UnifiedChoices"},{"#f":1}],"UnifiedChoices":[["ev",{"VAR?":"zaslava_quest_completed"},false,"==",{"VAR?":"zaslava_quest_assigned"},false,"==","&&","/ev",[{"->":".^.b","c":true},{"b":["\n","ev","str","^Нужна ли тебе помощь по хозяйству?","/str","/ev",{"*":".^.c-0","flg":20},{"->":".^.^.^.11"},{"c-0":["\n","^Я не здешний, но прибыл издалека, чтобы людям помогать. Быть может тебе нужно помочь что-то сделать по хозяйству? ","#","^speaker:","ev",{"VAR?":"player_name"},"out","/ev","^ ","/#","#","^portrait:player_default","/#","\n","^Как интересно! Хмм... дай подумать. Мне для отваров ингредиенты нужны, а грибы как раз закончились. Сходишь за ними в лес? ","#","^quest:zaslava ","/#","#","^speaker:","ev",{"VAR?":"npc"},"out","/ev","^ ","/#","#","^portrait:","ev",{"VAR?":"npc_portrait"},"out","/ev","/#","\n","^Конечно схожу. Только не подскажешь, где эти грибы растут. ","#","^speaker:","ev",{"VAR?":"player_name"},"out","/ev","^ ","/#","#","^portrait:player_default","/#","\n","^Иди в сторону леса до развилки с пещерой. На ней поверни налево, так ты придешь на поляну, где много грибов. ","#","^speaker:","ev",{"VAR?":"npc"},"out","/ev","^ ","/#","#","^portrait:","ev",{"VAR?":"npc_portrait"},"out","/ev","/#","\n","^Корзинки грибов тебе хватит? ","#","^speaker:","ev",{"VAR?":"player_name"},"out","/ev","^ ","/#","#","^portrait:player_default","/#","\n","^Ой, мне как-то неудобно тебя просить о таком. Мне и 6 штук будет достаточно ","#","^speaker:","ev",{"VAR?":"npc"},"out","/ev","^ ","/#","#","^portrait:","ev",{"VAR?":"npc_portrait"},"out","/ev","/#","\n","^Шесть так шесть ","#","^speaker:","ev",{"VAR?":"player_name"},"out","/ev","^ ","/#","#","^portrait:player_default","/#","\n",{"->":".^.^.^.^.^"},{"#f":5}]}]}],[{"->":".^.b"},{"b":["\n","ev",{"VAR?":"zaslava_quest_assigned"},true,"==",{"VAR?":"zaslava_quest_completed"},false,"==","&&","/ev",[{"->":".^.b","c":true},{"b":["\n",["ev",{"^->":"UnifiedChoices.0.10.b.10.b.1.$r1"},{"temp=":"$r"},"str",{"->":".^.s"},[{"#n":"$r1"}],"/str","/ev",{"*":".^.^.c-0","flg":18},{"s":["^Не подскажешь еще раз путь? ","#","^speaker:","ev",{"VAR?":"player_name"},"out","/ev","^ ","/#","#","^portrait:player_default","/#",{"->":"$r","var":true},null]}],{"->":".^.^.^.12"},{"c-0":["ev",{"^->":"UnifiedChoices.0.10.b.10.b.c-0.$r2"},"/ev",{"temp=":"$r"},{"->":".^.^.1.s"},[{"#n":"$r2"}],"\n","^Конечно! Поляна с грибами находится за деревней. Иди в сторону леса к развилке с пещерой, на ней поверни налево и выйдешь на поляну. ","#","^speaker:","ev",{"VAR?":"npc"},"out","/ev","^ ","/#","#","^portrait:","ev",{"VAR?":"npc_portrait"},"out","/ev","/#","\n","^Спасибо ","#","^speaker:","ev",{"VAR?":"player_name"},"out","/ev","^ ","/#","#","^portrait:player_default","/#","\n",{"->":"UnifiedChoices"},{"#f":5}]}]}],[{"->":".^.b"},{"b":["\n","ev",{"VAR?":"zaslava_quest_completed"},true,"==",{"VAR?":"zaslava_quest_finished"},false,"==","&&","/ev",[{"->":".^.b","c":true},{"b":["\n","ev","str","^Я собрал грибы","/str","/ev",{"*":".^.c-0","flg":20},{"->":".^.^.^.11"},{"c-0":["\n","^Вот, грибов тебе собрал. ","#","^speaker:","ev",{"VAR?":"player_name"},"out","/ev","^ ","/#","#","^portrait:player_default","/#","\n","^Спасибо тебе большое! ","#","^quest:zaslava ","/#","#","^speaker:","ev",{"VAR?":"npc"},"out","/ev","^ ","/#","#","^portrait:","ev",{"VAR?":"npc_portrait"},"out","/ev","/#","\n",{"->":"UnifiedChoices"},{"#f":5}]}]}],"nop","\n",{"->":".^.^.^.12"},null]}],"nop","\n",{"->":".^.^.^.11"},null]}],"nop","\n",["ev",{"^->":"UnifiedChoices.0.13.$r1"},{"temp=":"$r"},"str",{"->":".^.s"},[{"#n":"$r1"}],"/str","/ev",{"*":".^.^.c-0","flg":2},{"s":["^Расскажи про эти края ","#","^speaker:","ev",{"VAR?":"player_name"},"out","/ev","^ ","/#","#","^portrait:player_default","/#",{"->":"$r","var":true},null]}],["ev",{"^->":"UnifiedChoices.0.14.$r1"},{"temp=":"$r"},"str",{"->":".^.s"},[{"#n":"$r1"}],"/str","/ev",{"*":".^.^.c-1","flg":18},{"s":["^Чем занимаешься сегодня вечером? ","#","^speaker:","ev",{"VAR?":"player_name"},"out","/ev","^ ","/#","#","^portrait:player_default","/#",{"->":"$r","var":true},null]}],["ev",{"^->":"UnifiedChoices.0.15.$r1"},{"temp=":"$r"},"str",{"->":".^.s"},[{"#n":"$r1"}],"/str","/ev",{"*":".^.^.c-2","flg":18},{"s":["^До скорого ","#","^speaker:","ev",{"VAR?":"player_name"},"out","/ev","^ ","/#","#","^portrait:player_default","/#",{"->":"$r","var":true},null]}],{"c-0":["ev",{"^->":"UnifiedChoices.0.c-0.$r2"},"/ev",{"temp=":"$r"},{"->":".^.^.13.s"},[{"#n":"$r2"}],"\n","^Красивый край: чистый воздух, умиротворение. Одно лишь плохо, что разбойников последнее время много. ","#","^speaker:","ev",{"VAR?":"npc"},"out","/ev","^ ","/#","#","^portrait:","ev",{"VAR?":"npc_portrait"},"out","/ev","/#","\n",{"->":".^.^.^"},{"#f":5}],"c-1":["ev",{"^->":"UnifiedChoices.0.c-1.$r2"},"/ev",{"temp=":"$r"},{"->":".^.^.14.s"},[{"#n":"$r2"}],"\n","^Убираюсь по дому, готовлю отвары ну и разное по мелочи. ","#","^speaker:","ev",{"VAR?":"npc"},"out","/ev","^ ","/#","#","^portrait:","ev",{"VAR?":"npc_portrait"},"out","/ev","/#","\n","^Сходить погулять по лесу со мной не хочешь? ","#","^speaker:","ev",{"VAR?":"player_name"},"out","/ev","^ ","/#","#","^portrait:player_default","/#","\n","^Извини, слишком занята, давай как-нибудь в другой раз ","#","^speaker:","ev",{"VAR?":"npc"},"out","/ev","^ ","/#","#","^portrait:","ev",{"VAR?":"npc_portrait"},"out","/ev","/#","\n",{"->":".^.^.^"},{"#f":5}],"c-2":["ev",{"^->":"UnifiedChoices.0.c-2.$r2"},"/ev",{"temp=":"$r"},{"->":".^.^.15.s"},[{"#n":"$r2"}],"\n","^До встречи! ","#","^speaker:","ev",{"VAR?":"npc"},"out","/ev","^ ","/#","#","^portrait:","ev",{"VAR?":"npc_portrait"},"out","/ev","/#","\n","end",{"#f":5}]}],{"#f":1}],"global decl":["ev","str","^Ярослав","/str",{"VAR=":"player_name"},false,{"VAR=":"bogomir_quest_assigned"},false,{"VAR=":"bogomir_quest_completed"},false,{"VAR=":"bogomir_quest_finished"},false,{"VAR=":"zaslava_quest_assigned"},false,{"VAR=":"zaslava_quest_completed"},false,{"VAR=":"zaslava_quest_finished"},false,{"VAR=":"yakov_quest_assigned"},false,{"VAR=":"yakov_quest_completed"},false,{"VAR=":"yakov_quest_finished"},false,{"VAR=":"mikolaMemories_quest_assigned"},false,{"VAR=":"mikolaMemories_quest_completed"},false,{"VAR=":"mikolaMemories_quest_finished"},false,{"VAR=":"mikolaMemories_player_losed"},"str","^Заслава","/str",{"VAR=":"npc"},"str","^zaslava_default","/str",{"VAR=":"npc_portrait"},false,{"VAR=":"talking"},"/ev","end",null],"#f":1}],"listDefs":{}}